pylupnt-0.0.4.dist-info/METADATA
pylupnt-0.0.4.dist-info/RECORD
pylupnt-0.0.4.dist-info/WHEEL
pylupnt-0.0.4.dist-info/licenses/LICENSE
lib64/libnodesoup.a
lib64/libmatplot.a
lib64/cmake/autodiff/autodiffConfig.cmake
lib64/cmake/autodiff/autodiffConfigVersion.cmake
lib64/cmake/autodiff/autodiffTargets.cmake
lib64/cmake/LuPNT/LuPNTTargets.cmake
lib64/cmake/LuPNT/LuPNTConfigVersion.cmake
lib64/cmake/LuPNT/LuPNTConfig.cmake
lib64/cmake/LuPNT/LuPNTTargets-release.cmake
lib64/cmake/cspice-1.0/cspiceConfig.cmake
lib64/cmake/cspice-1.0/cspiceConfigVersion.cmake
lib64/cmake/cspice-1.0/cspiceTargets.cmake
lib64/cmake/cspice-1.0/cspiceTargets-release.cmake
lib64/cmake/Matplot++/Matplot++Config.cmake
lib64/cmake/Matplot++/Matplot++Targets-release.cmake
lib64/cmake/Matplot++/Matplot++Targets.cmake
lib64/cmake/Matplot++/Matplot++ConfigVersion.cmake
lib64/LuPNT/libLuPNT.a
lib64/cspice-1.0/libcspice.a
pylupnt/_pylupnt.pyi
pylupnt/_pylupnt.cpython-310-x86_64-linux-gnu.so
pylupnt/math_utils.py
pylupnt/__init__.py
pylupnt/download_data.py
pylupnt/utils.py
pylupnt/plot/_plotly.py
pylupnt/plot/_mpl.py
pylupnt/plot/__init__.py
pylupnt/plot/colorpalette.png
pylupnt/scenarios/__init__.py
pylupnt/scenarios/pathfinder.py
pylupnt/render/_blender.py
pylupnt/render/__init__.py
include/matplot/matplot.h
include/matplot/detail/exports.h
include/matplot/detail/config.h
include/matplot/core/figure_registry.h
include/matplot/core/axes_object.h
include/matplot/core/figure_type.h
include/matplot/core/axis_type.h
include/matplot/core/legend.h
include/matplot/core/line_spec.h
include/matplot/core/axes_type.h
include/matplot/axes_objects/vectors.h
include/matplot/axes_objects/function_line.h
include/matplot/axes_objects/contours.h
include/matplot/axes_objects/string_function.h
include/matplot/axes_objects/box_chart.h
include/matplot/axes_objects/histogram.h
include/matplot/axes_objects/bars.h
include/matplot/axes_objects/matrix.h
include/matplot/axes_objects/error_bar.h
include/matplot/axes_objects/stair.h
include/matplot/axes_objects/network.h
include/matplot/axes_objects/labels.h
