Metadata-Version: 2.1
Name: pylupnt
Version: 0.0.4
Summary: Lunar Positioning, Navigation, and Timing (PNT) library
Keywords: pybind11,cibuildwheel,c++,pypi,numpy,simple,example,wheel,pypi,conda-forge
Author-Email: "Guillem Casadesus Vila, Keidai Iiyama" <guillemc@stanford.edu;kiiyama@stanford.edu>
Maintainer-Email: "Guillem Casadesus Vila, Keidai Iiyama" <guillemc@stanford.edu;kiiyama@stanford.edu>
License: MIT
Classifier: Programming Language :: C++
Classifier: Programming Language :: Python :: 3 :: Only
Classifier: Programming Language :: Python :: 3.9
Classifier: Programming Language :: Python :: 3.10
Classifier: Programming Language :: Python :: 3.11
Classifier: Programming Language :: Python :: 3.12
Classifier: Programming Language :: Python :: Implementation :: CPython
Classifier: Programming Language :: Python :: Implementation :: PyPy
Classifier: Operating System :: MacOS :: MacOS X
Classifier: Operating System :: Microsoft :: Windows
Classifier: Operating System :: POSIX :: Linux
Classifier: License :: OSI Approved :: MIT License
Project-URL: Github, https://github.com/Stanford-NavLab/LuPNT
Project-URL: Documentation, https://lupnt.readthedocs.io
Requires-Python: <3.13,>=3.10
Requires-Dist: h5py
Requires-Dist: ipykernel
Requires-Dist: mathutils
Requires-Dist: matplotlib
Requires-Dist: mypy
Requires-Dist: nbformat
Requires-Dist: numpy
Requires-Dist: pandas
Requires-Dist: Pillow
Requires-Dist: plotly
Requires-Dist: requests
Requires-Dist: scikit-learn
Requires-Dist: tqdm
Requires-Dist: pytest; extra == "test"
Requires-Dist: cmake; extra == "docs"
Requires-Dist: breathe; extra == "docs"
Requires-Dist: sphinx_rtd_theme; extra == "docs"
Requires-Dist: notebook; extra == "docs"
Requires-Dist: sphinx; extra == "docs"
Requires-Dist: exhale; extra == "docs"
Requires-Dist: breathe; extra == "docs"
Requires-Dist: m2r; extra == "docs"
Requires-Dist: nbsphinx; extra == "docs"
Requires-Dist: nbsphinx-link; extra == "docs"
Requires-Dist: jinja2; extra == "docs"
Requires-Dist: lxml_html_clean; extra == "docs"
Provides-Extra: test
Provides-Extra: docs
